crypto_dot_com/__init__.py
crypto_dot_com/client.py
crypto_dot_com/data_models.py
crypto_dot_com/enums.py
crypto_dot_com/exceptions.py
crypto_dot_com/export.py
crypto_dot_com/request_builder.py
crypto_dot_com/settings.py
crypto_dot_com/utils.py
crypto_dot_com/data_models/__init__.py
crypto_dot_com/data_models/crypto_dot_com.py
crypto_dot_com/data_models/mappings.py
crypto_dot_com/data_models/order_history.py
crypto_dot_com/data_models/request_message.py
crypto_dot_com/data_models/response.py
crypto_dot_com/data_models/standard.py
crypto_dot_com/data_models/summary.py
python_crypto_dot_com_sdk-1.1.1.dist-info/LICENSE
python_crypto_dot_com_sdk-1.1.1.dist-info/METADATA
python_crypto_dot_com_sdk-1.1.1.dist-info/WHEEL
python_crypto_dot_com_sdk-1.1.1.dist-info/top_level.txt
python_crypto_dot_com_sdk-1.1.1.dist-info/RECORD
