Metadata-Version: 2.1
Name: python-crypto-dot-com-sdk
Version: 1.1.1
Summary: A simple python wrapper for crypto.com API
Home-page: https://github.com/javadebadi/python-crypto-dot-com-sdk
Author: Javad Ebadi
Author-email: javad@javadebadi.com
License: Apache 2.0
Requires-Python: >=3.11
License-File: LICENSE
Requires-Dist: requests
Requires-Dist: xarizmi
